submit_code/__init__.py
submit_code/send_code.py
submit_code/web-project-c3c1a-firebase-adminsdk-9j2mf-e202997418.json
submit_code-0.2.2.dist-info/METADATA
submit_code-0.2.2.dist-info/WHEEL
submit_code-0.2.2.dist-info/top_level.txt
submit_code-0.2.2.dist-info/RECORD
